{
  "file": "option_05_jp.pbd",
  "size": 116402,
  "kind": "pbd_namespace",
  "pages": [
    "t_page0",
    "t_page0__caf9b48e",
    "t_page0__ee596594",
    "t_page1",
    "t_page1__caf9b48e",
    "t_page1__ee596594",
    "t_page2",
    "t_page2__caf9b48e",
    "t_page2__ee596594",
    "t_page3",
    "t_page3__caf9b48e",
    "t_page3__ee596594",
    "t_page4",
    "t_page4__caf9b48e",
    "t_page4__ee596594",
    "t_page5",
    "t_page5__caf9b48e",
    "t_page5__ee596594",
    "t_page6",
    "t_page6__caf9b48e",
    "t_page6__ee596594",
    "t_page7",
    "t_page7__caf9b48e",
    "t_page7__ee596594",
    "t_page8",
    "t_page8__caf9b48e",
    "t_page8__ee596594",
    "t_page9",
    "t_page9__caf9b48e",
    "t_page9__ee596594"
  ],
  "layer_count": 67,
  "layers": [
    "t_after_keep",
    "t_after_stop",
    "t_autost_n",
    "t_autost_s",
    "t_autost_v",
    "t_back",
    "t_back__a3e396a4",
    "t_back__caf9b48e",
    "t_back__ee596594",
    "t_check",
    "t_col_hwin",
    "t_col_ntext",
    "t_col_owin",
    "t_col_rtext",
    "t_col_win",
    "t_dis_hwin",
    "t_font",
    "t_numbase",
    "t_page0",
    "t_page0__caf9b48e",
    "t_page0__ee596594",
    "t_page1",
    "t_page1__caf9b48e",
    "t_page1__ee596594",
    "t_page2",
    "t_page2__caf9b48e",
    "t_page2__ee596594",
    "t_page3",
    "t_page3__caf9b48e",
    "t_page3__ee596594",
    "t_page4",
    "t_page4__caf9b48e",
    "t_page4__ee596594",
    "t_page5",
    "t_page5__caf9b48e",
    "t_page5__ee596594",
    "t_page6",
    "t_page6__caf9b48e",
    "t_page6__ee596594",
    "t_page7",
    "t_page7__caf9b48e",
    "t_page7__ee596594",
    "t_page8",
    "t_page8__caf9b48e",
    "t_page8__ee596594",
    "t_page9",
    "t_page9__caf9b48e",
    "t_page9__ee596594",
    "t_rad",
    "t_rbt",
    "t_reset",
    "t_reset__a3e396a4",
    "t_reset__caf9b48e",
    "t_reset__ee596594",
    "t_revert",
    "t_sel",
    "t_skip_all",
    "t_skip_readed",
    "t_slider",
    "t_text",
    "t_title",
    "t_title__a3e396a4",
    "t_title__caf9b48e",
    "t_title__ee596594",
    "t_value",
    "t_wchar",
    "t_wtime"
  ],
  "buttons": [],
  "commands": [
    "Current.cmd(",
    "Current.cmd(\"reset\")",
    "Current.cmd(\"resetColor\")",
    "Current.cmd(\"selectBasicOptionValue/afterauto\")",
    "Current.cmd(\"selectBasicOptionValue/afterskip\")",
    "Current.cmd(\"selectBasicOptionValue/autovwait\")",
    "Current.cmd(\"selectBasicOptionValue/ctrlskip\")",
    "Current.cmd(\"selectBasicOptionValue/nohwindow\")",
    "Current.cmd(\"selectBasicOptionValue/skipall\")",
    "Current.cmd(\"selectCurrentColor/0\")",
    "Current.cmd(\"selectCurrentColor/1\")",
    "Current.cmd(\"selectCurrentColor/2\")",
    "Current.cmd(\"selectCurrentColor/3\")",
    "Current.cmd(\"selectCurrentColor/4\")",
    "Current.cmd(\"selectFont\")",
    "Current.cmd(\"setBasicOptionValue/afterauto/off\")",
    "Current.cmd(\"setBasicOptionValue/afterauto/on\")",
    "Current.cmd(\"setBasicOptionValue/afterauto/toggle\")",
    "Current.cmd(\"setBasicOptionValue/afterskip/off\")",
    "Current.cmd(\"setBasicOptionValue/afterskip/on\")",
    "Current.cmd(\"setBasicOptionValue/afterskip/toggle\")",
    "Current.cmd(\"setBasicOptionValue/autovwait/0\")",
    "Current.cmd(\"setBasicOptionValue/autovwait/1\")",
    "Current.cmd(\"setBasicOptionValue/autovwait/2\")",
    "Current.cmd(\"setBasicOptionValue/ctrlskip/off\")",
    "Current.cmd(\"setBasicOptionValue/ctrlskip/on\")",
    "Current.cmd(\"setBasicOptionValue/ctrlskip/toggle\")",
    "Current.cmd(\"setBasicOptionValue/nohwindow/off\")",
    "Current.cmd(\"setBasicOptionValue/nohwindow/on\")",
    "Current.cmd(\"setBasicOptionValue/nohwindow/toggle\")",
    "Current.cmd(\"setBasicOptionValue/skipall/off\")",
    "Current.cmd(\"setBasicOptionValue/skipall/on\")",
    "Current.cmd(\"setBasicOptionValue/skipall/toggle\")",
    "Current.cmd(\"setColorDirect\")",
    "Current.cmd(\"toggleSpeechEnabled\")",
    "Current.func(",
    "Current.func(\"changeBasicSlider\")",
    "Current.func(\"onSpeedSliderChange\")"
  ],
  "bindings": [
    "changeBasicSlider",
    "onSpeedSliderChange",
    "reset",
    "resetColor",
    "selectBasicOptionValue/afterauto",
    "selectBasicOptionValue/afterskip",
    "selectBasicOptionValue/autovwait",
    "selectBasicOptionValue/ctrlskip",
    "selectBasicOptionValue/nohwindow",
    "selectBasicOptionValue/skipall",
    "selectCurrentColor/0",
    "selectCurrentColor/1",
    "selectCurrentColor/2",
    "selectCurrentColor/3",
    "selectCurrentColor/4",
    "selectFont",
    "setBasicOptionValue/afterauto/off",
    "setBasicOptionValue/afterauto/on",
    "setBasicOptionValue/afterauto/toggle",
    "setBasicOptionValue/afterskip/off",
    "setBasicOptionValue/afterskip/on",
    "setBasicOptionValue/afterskip/toggle",
    "setBasicOptionValue/autovwait/0",
    "setBasicOptionValue/autovwait/1",
    "setBasicOptionValue/autovwait/2",
    "setBasicOptionValue/ctrlskip/off",
    "setBasicOptionValue/ctrlskip/on",
    "setBasicOptionValue/ctrlskip/toggle",
    "setBasicOptionValue/nohwindow/off",
    "setBasicOptionValue/nohwindow/on",
    "setBasicOptionValue/nohwindow/toggle",
    "setBasicOptionValue/skipall/off",
    "setBasicOptionValue/skipall/on",
    "setBasicOptionValue/skipall/toggle",
    "setColorDirect",
    "toggleSpeechEnabled"
  ]
}